nexusview/__init__.py
nexusview/_version.py
nexusview/h5reader.py
nexusview/nxview.py
nexusview-0.1.4.dist-info/LICENSE.rst
nexusview-0.1.4.dist-info/METADATA
nexusview-0.1.4.dist-info/WHEEL
nexusview-0.1.4.dist-info/entry_points.txt
nexusview-0.1.4.dist-info/RECORD
