Metadata-Version: 2.1
Name: nexusview
Version: 0.1.4
Summary: A utility to explore the content of NeXuS/HDF5 files
License: GPL3
Author: Nicolas Soler
Author-email: nsoler@cells.es
Requires-Python: >=3.12,<4.0
Classifier: License :: Other/Proprietary License
Classifier: Programming Language :: Python :: 3
Classifier: Programming Language :: Python :: 3.12
Requires-Dist: h5py (>=3.13.0,<4.0.0)
Requires-Dist: pandas (>=2.2.3,<3.0.0)
Requires-Dist: termcolor (>=3.0.1,<4.0.0)
